{
  "$schema": "https://developer.microsoft.com/json-schemas/fabric/item/report/definition/visualContainer/2.1.0/schema.json",
  "name": "498552989eb1b1e5dc0f",
  "position": {
    "x": 20,
    "y": 196,
    "z": 4100,
    "height": 140,
    "width": 980,
    "tabOrder": 4100
  },
  "visual": {
    "visualType": "columnChart",
    "drillFilterOtherVisuals": true,
    "visualContainerObjects": {
      "background": [
        {
          "properties": {
            "show": {
              "expr": {
                "Literal": {
                  "Value": "true"
                }
              }
            },
            "color": {
              "solid": {
                "color": {
                  "expr": {
                    "Literal": {
                      "Value": "'#FFFFFF'"
                    }
                  }
                }
              }
            },
            "transparency": {
              "expr": {
                "Literal": {
                  "Value": "0D"
                }
              }
            }
          }
        }
      ],
      "border": [
        {
          "properties": {
            "show": {
              "expr": {
                "Literal": {
                  "Value": "true"
                }
              }
            },
            "color": {
              "solid": {
                "color": {
                  "expr": {
                    "Literal": {
                      "Value": "'#DCE6F2'"
                    }
                  }
                }
              }
            },
            "radius": {
              "expr": {
                "Literal": {
                  "Value": "12D"
                }
              }
            },
            "width": {
              "expr": {
                "Literal": {
                  "Value": "1D"
                }
              }
            }
          }
        }
      ],
      "dropShadow": [
        {
          "properties": {
            "show": {
              "expr": {
                "Literal": {
                  "Value": "true"
                }
              }
            },
            "preset": {
              "expr": {
                "Literal": {
                  "Value": "'Custom'"
                }
              }
            },
            "position": {
              "expr": {
                "Literal": {
                  "Value": "'Outer'"
                }
              }
            },
            "color": {
              "solid": {
                "color": {
                  "expr": {
                    "Literal": {
                      "Value": "'#0B1E3D'"
                    }
                  }
                }
              }
            },
            "transparency": {
              "expr": {
                "Literal": {
                  "Value": "65D"
                }
              }
            },
            "shadowSpread": {
              "expr": {
                "Literal": {
                  "Value": "2D"
                }
              }
            },
            "shadowBlur": {
              "expr": {
                "Literal": {
                  "Value": "14D"
                }
              }
            },
            "angle": {
              "expr": {
                "Literal": {
                  "Value": "135D"
                }
              }
            },
            "shadowDistance": {
              "expr": {
                "Literal": {
                  "Value": "3D"
                }
              }
            }
          }
        }
      ]
    },
    "query": {
      "queryState": {
        "Category": {
          "projections": [
            {
              "field": {
                "Column": {
                  "Expression": {
                    "SourceRef": {
                      "Entity": "DeviceHealth"
                    }
                  },
                  "Property": "DeviceType"
                }
              },
              "queryRef": "DeviceHealth.DeviceType",
              "nativeQueryRef": "DeviceType",
              "active": true
            }
          ]
        },
        "Y": {
          "projections": [
            {
              "field": {
                "Measure": {
                  "Expression": {
                    "SourceRef": {
                      "Entity": "DeviceHealth"
                    }
                  },
                  "Property": "Sensor Active"
                }
              },
              "queryRef": "DeviceHealth.Sensor Active",
              "nativeQueryRef": "Sensor Active"
            },
            {
              "field": {
                "Measure": {
                  "Expression": {
                    "SourceRef": {
                      "Entity": "DeviceHealth"
                    }
                  },
                  "Property": "Sensor Impaired"
                }
              },
              "queryRef": "DeviceHealth.Sensor Impaired",
              "nativeQueryRef": "Sensor Impaired"
            },
            {
              "field": {
                "Measure": {
                  "Expression": {
                    "SourceRef": {
                      "Entity": "DeviceHealth"
                    }
                  },
                  "Property": "Sensor Not Reporting"
                }
              },
              "queryRef": "DeviceHealth.Sensor Not Reporting",
              "nativeQueryRef": "Sensor Not Reporting"
            }
          ]
        }
      }
    },
    "objects": {
      "dataPoint": [
        {
          "properties": {
            "fill": {
              "solid": {
                "color": {
                  "expr": {
                    "Literal": {
                      "Value": "'#107C10'"
                    }
                  }
                }
              }
            }
          },
          "selector": {
            "metadata": "DeviceHealth.Sensor Active"
          }
        },
        {
          "properties": {
            "fill": {
              "solid": {
                "color": {
                  "expr": {
                    "Literal": {
                      "Value": "'#F7A500'"
                    }
                  }
                }
              }
            }
          },
          "selector": {
            "metadata": "DeviceHealth.Sensor Impaired"
          }
        },
        {
          "properties": {
            "fill": {
              "solid": {
                "color": {
                  "expr": {
                    "Literal": {
                      "Value": "'#D13438'"
                    }
                  }
                }
              }
            }
          },
          "selector": {
            "metadata": "DeviceHealth.Sensor Not Reporting"
          }
        }
      ],
      "title": [
        {
          "properties": {
            "show": {
              "expr": {
                "Literal": {
                  "Value": "true"
                }
              }
            },
            "text": {
              "expr": {
                "Literal": {
                  "Value": "'Sensor connectivity (green = Active / amber = Impaired / red = Not reporting)'"
                }
              }
            },
            "fontSize": {
              "expr": {
                "Literal": {
                  "Value": "12D"
                }
              }
            },
            "bold": {
              "expr": {
                "Literal": {
                  "Value": "true"
                }
              }
            },
            "titleWrap": {
              "expr": {
                "Literal": {
                  "Value": "true"
                }
              }
            },
            "heading": {
              "expr": {
                "Literal": {
                  "Value": "'H3'"
                }
              }
            }
          }
        }
      ],
      "labels": [
        {
          "properties": {
            "show": {
              "expr": {
                "Literal": {
                  "Value": "true"
                }
              }
            }
          }
        }
      ]
    }
  }
}