{
  "$schema": "https://developer.microsoft.com/json-schemas/fabric/item/report/definition/visualContainer/2.1.0/schema.json",
  "name": "63717b9c4aeca6a9ef95",
  "position": {
    "x": 20,
    "y": 100,
    "z": 5000,
    "height": 108,
    "width": 980,
    "tabOrder": 5000
  },
  "visual": {
    "visualType": "cardVisual",
    "drillFilterOtherVisuals": true,
    "visualContainerObjects": {
      "background": [
        {
          "properties": {
            "show": {
              "expr": {
                "Literal": {
                  "Value": "true"
                }
              }
            },
            "color": {
              "solid": {
                "color": {
                  "expr": {
                    "Literal": {
                      "Value": "'#FFFFFF'"
                    }
                  }
                }
              }
            },
            "transparency": {
              "expr": {
                "Literal": {
                  "Value": "0D"
                }
              }
            }
          }
        }
      ],
      "border": [
        {
          "properties": {
            "show": {
              "expr": {
                "Literal": {
                  "Value": "true"
                }
              }
            },
            "color": {
              "solid": {
                "color": {
                  "expr": {
                    "Literal": {
                      "Value": "'#DCE6F2'"
                    }
                  }
                }
              }
            },
            "radius": {
              "expr": {
                "Literal": {
                  "Value": "12D"
                }
              }
            },
            "width": {
              "expr": {
                "Literal": {
                  "Value": "1D"
                }
              }
            }
          }
        }
      ],
      "dropShadow": [
        {
          "properties": {
            "show": {
              "expr": {
                "Literal": {
                  "Value": "true"
                }
              }
            },
            "preset": {
              "expr": {
                "Literal": {
                  "Value": "'Custom'"
                }
              }
            },
            "position": {
              "expr": {
                "Literal": {
                  "Value": "'Outer'"
                }
              }
            },
            "color": {
              "solid": {
                "color": {
                  "expr": {
                    "Literal": {
                      "Value": "'#0B1E3D'"
                    }
                  }
                }
              }
            },
            "transparency": {
              "expr": {
                "Literal": {
                  "Value": "65D"
                }
              }
            },
            "shadowSpread": {
              "expr": {
                "Literal": {
                  "Value": "2D"
                }
              }
            },
            "shadowBlur": {
              "expr": {
                "Literal": {
                  "Value": "14D"
                }
              }
            },
            "angle": {
              "expr": {
                "Literal": {
                  "Value": "135D"
                }
              }
            },
            "shadowDistance": {
              "expr": {
                "Literal": {
                  "Value": "3D"
                }
              }
            }
          }
        }
      ]
    },
    "query": {
      "queryState": {
        "Data": {
          "projections": [
            {
              "field": {
                "Measure": {
                  "Expression": {
                    "SourceRef": {
                      "Entity": "DeviceHealth"
                    }
                  },
                  "Property": "Mobile Devices"
                }
              },
              "queryRef": "DeviceHealth.Mobile Devices",
              "nativeQueryRef": "Mobile Devices"
            },
            {
              "field": {
                "Measure": {
                  "Expression": {
                    "SourceRef": {
                      "Entity": "DeviceHealth"
                    }
                  },
                  "Property": "Android"
                }
              },
              "queryRef": "DeviceHealth.Android",
              "nativeQueryRef": "Android"
            },
            {
              "field": {
                "Measure": {
                  "Expression": {
                    "SourceRef": {
                      "Entity": "DeviceHealth"
                    }
                  },
                  "Property": "iOS"
                }
              },
              "queryRef": "DeviceHealth.iOS",
              "nativeQueryRef": "iOS"
            },
            {
              "field": {
                "Measure": {
                  "Expression": {
                    "SourceRef": {
                      "Entity": "DeviceHealth"
                    }
                  },
                  "Property": "MDM Enrolled"
                }
              },
              "queryRef": "DeviceHealth.MDM Enrolled",
              "nativeQueryRef": "MDM Enrolled"
            },
            {
              "field": {
                "Measure": {
                  "Expression": {
                    "SourceRef": {
                      "Entity": "DeviceHealth"
                    }
                  },
                  "Property": "MAM Enrolled"
                }
              },
              "queryRef": "DeviceHealth.MAM Enrolled",
              "nativeQueryRef": "MAM Enrolled"
            },
            {
              "field": {
                "Measure": {
                  "Expression": {
                    "SourceRef": {
                      "Entity": "DeviceHealth"
                    }
                  },
                  "Property": "App Outdated"
                }
              },
              "queryRef": "DeviceHealth.App Outdated",
              "nativeQueryRef": "App Outdated"
            }
          ]
        }
      }
    },
    "objects": {
      "layout": [
        {
          "properties": {
            "columnCount": {
              "expr": {
                "Literal": {
                  "Value": "6L"
                }
              }
            },
            "style": {
              "expr": {
                "Literal": {
                  "Value": "'Cards'"
                }
              }
            }
          }
        }
      ],
      "categoryLabel": [
        {
          "properties": {
            "fontSize": {
              "expr": {
                "Literal": {
                  "Value": "9D"
                }
              }
            },
            "wordWrap": {
              "expr": {
                "Literal": {
                  "Value": "true"
                }
              }
            }
          }
        }
      ],
      "calloutValue": [
        {
          "properties": {
            "fontSize": {
              "expr": {
                "Literal": {
                  "Value": "20D"
                }
              }
            },
            "bold": {
              "expr": {
                "Literal": {
                  "Value": "true"
                }
              }
            }
          }
        }
      ]
    }
  }
}